README.rst
setup.py
dbtunnel/__init__.py
django_dbtunnel.egg-info/PKG-INFO
django_dbtunnel.egg-info/SOURCES.txt
django_dbtunnel.egg-info/dependency_links.txt
django_dbtunnel.egg-info/requires.txt
django_dbtunnel.egg-info/top_level.txt