Metadata-Version: 1.1
Name: django-dbtunnel
Version: 1.0.0
Summary: Connect to and use a remote database over an SSH tunnel in Django.
Home-page: https://github.com/mvx24/django-dbtunnel
Author: mvx24
Author-email: cram2400@gmail.com
License: MIT
Keywords: ssh tunnel production database django paramiko mysql postgresql
Platform: UNKNOWN
Classifier: Development Status :: 5 - Production/Stable
Classifier: Environment :: Console
Classifier: Framework :: Django
Classifier: License :: OSI Approved :: MIT License
Classifier: Operating System :: MacOS :: MacOS X
Classifier: Operating System :: POSIX
Classifier: Operating System :: Unix
Classifier: Programming Language :: Python :: 2.7
Classifier: Programming Language :: Python :: 2 :: Only
Classifier: Topic :: System :: Systems Administration
